cgstatistical/__init__.py
cgstatistical/cgstatistic.py
cgstatistical/util.py
cgstatistical-0.0.5.dist-info/LICENSE
cgstatistical-0.0.5.dist-info/METADATA
cgstatistical-0.0.5.dist-info/WHEEL
cgstatistical-0.0.5.dist-info/top_level.txt
cgstatistical-0.0.5.dist-info/RECORD
