Metadata-Version: 2.1
Name: cgstatistical
Version: 0.0.5
Summary: CBio-Gres Statistical Tests
Home-page: https://github.com/dimmykarson/CGStatistic
Author: Jackson Prado Lima, Dimmy Magalhaes
Author-email: dimmyk@gmail.com
License: UNKNOWN
Platform: UNKNOWN
Classifier: Programming Language :: Python :: 3
Classifier: License :: OSI Approved :: MIT License
Classifier: Operating System :: OS Independent
Requires-Dist: seaborn
Requires-Dist: pandas
Requires-Dist: rpy2
Requires-Dist: matplotlib
Requires-Dist: numpy
